{
"results": [
 {
 "name": "Tạ Tuyết Ngân - Ăn Vặt & Trà Sữa",
 "img": "https://images.foody.vn/res/g9/88316/prof/s576x330/foody-mobile-7z5gppcs-jpg-720-635948586117897873.jpg",
 "address": "308/10/8 Nguyễn Tri Phương, Quận , TP.HCM",
 "type": "Ăn vặt/Vỉa hè",
 "location":
 {
  "lat":10.763141,
  "lng":106.669191
 }
 },
 {
 "name": "Osaka - Cơm Thố Nhật Bản",
 "img": "https://images.foody.vn/res/g19/185028/prof/s576x330/foody-mobile-rkzfp07z-jpg-140-636129280000057937.jpg",
 "address": "64 Nguyễn Thời Trung, P. 6, Quận 5, TP.HCM",
 "type": "Quán ăn",
 "location":
 {
  "lat":10.752688,
  "lng":106.669874
 }
 },
 {
 "name": "Luxe Đại Phát Cafe & Bakery - Nguyễn Trãi",
 "img": "https://images.foody.vn/res/g7/68358/prof/s576x330/foody-upload-api-foody-mobile-57-jpg-180723113502.jpg",
 "address": "515 - 517 Nguyễn Trãi, Quận 5, TP. HCM",
 "type": "Café/Dessert",
 "location":
 {
  "lat":10.7543297,
  "lng":106.6669412
 }
 },
 {
 "name": "Trà Sữa Gong Cha - 貢茶 - An Dương Vương",
 "img": "https://images.foody.vn/res/g69/681685/prof/s576x330/foody-mobile--a460937a2ba290c68e4-537-636386688358758262.jpg",
 "address": "498 An Dương Vương, P. 4, Quận 5, TP. HCM",
 "type": "Café/Dessert",
 "location":
 {
  "lat":10.758271,
  "lng":106.6751843
 }
 },
 {
 "name": "Trà Đào Momo - Trần Phú",
 "img": "http://sunhouse.com.vn/pic/news/1838_cach_lam_tra_dao_cam_xa_ngon_nhu_mua_ngoai_tiem.jpg",
 "address": "401B Trần Phú, P. 7, Quận 5, TP. HCM",
 "type": "Café/Dessert",
 "location":
 {
  "lat":10.7542587,
  "lng":106.6713456
 }
 },
 {
 "name": "101 Tea & Coffee - Nguyễn Biểu",
 "img": "https://images.foody.vn/res/g30/290437/prof/s576x330/foody-mobile-2-jpg-237-636148164539305148.jpg",
 "address": "249 Nguyễn Biểu, P. 2, Quận 5, TP. HCM",
 "type": "Café/Dessert",
 "location":
 {
  "lat":10.758149,
  "lng":106.6829814
 }
 },
 {
 "name": "Uncle Tea - Trà Đài Loan - Trần Hưng Đạo",
 "img": "https://images.foody.vn/res/g29/283537/prof/s576x330/foody-mobile-12-jpg.jpg",
 "address": "612 Trần Hưng Đạo, P. 2, Quận 5, TP. HCM",
 "type": "Café/Dessert",
 "location":
 {
  "lat":10.7547957,
  "lng":106.6764404
 }
 },
 {
 "name": "Uncle Tea - Trà Đài Loan - Nguyễn Trãi",
 "img": "https://images.foody.vn/res/g67/661626/prof/s576x330/foody-mobile-img_6215-jpg-964-636359732566903457.jpg",
 "address": "535 Nguyễn Trãi, P. 7, Quận 5, TP. HCM",
 "type": "Café/Dessert",
 "location":
 {
  "lat":10.7542714,
  "lng":106.6665552
 }
 },
 {
 "name": "Mato House - Taiwan Healthy Tea",
 "img": "https://images.foody.vn/video/s800x450/foody-img_3154-636488533762209905.jpg",
 "address": "319 Nguyễn Trãi, P. 7 Q.5, Quận 5, TP. HCM",
 "type": "Café/Dessert",
 "location":
 {
  "lat":10.7560078,
  "lng":106.6731557
 }
 },
 {
 "name": "Osu Foods & Drinks",
 "img": "https://images.foody.vn/res/g70/692656/prof/s576x330/foody-mobile-3-jpg.jpg",
 "address": "112 Trần Hưng Đạo, P. 7, Quận 5, TP. HCM",
 "type": "Café/Dessert",
 "location":
 {
  "lat":10.7528068,
  "lng":106.6674311
 }
 },
 {
 "name": "Chè Tường Phong",
 "img": "https://images.foody.vn/res/g2/14506/prof/s576x330/foody-mobile-mobile-jpg-872-635761949271681192.jpg",
 "address": "83 An Điềm, Quận 5, TP. HCM",
 "type": "Café/Dessert",
 "location":
 {
  "lat":10.7514304,
  "lng":106.6628788
 }
 },
 {
 "name": "Trà Sữa Tiên Hưởng - Nguyễn Tri Phương",
 "img": "https://images.foody.vn/res/g3/22947/prof/s576x330/foody-mobile-f-jpg-944-635762612509498108.jpg",
 "address": "138B Nguyễn Tri Phương, Quận 5, TP. HCM",
 "type": "Café/Dessert",
 "location":
 {
  "lat":10.7589045,
  "lng":106.667044
 }
 },
 {
 "name": "Trà Sữa Tiên Hưởng - Trần Hưng Đạo",
 "img": "https://images.foody.vn/res/g1/7164/prof/s576x330/foody-mobile-9-1-jpg-764-635738697160550063.jpg",
 "address": "789 Trần Hưng Đạo, P. 1, Quận 5, TP. HCM",
 "type": "Café/Dessert",
 "location":
 {
  "lat":10.7551682,
  "lng":106.6791612
 }
 },
 {
 "name": "Xúc Xắc Xoay Coffee",
 "img": "https://images.foody.vn/res/g4/34535/prof/s576x330/foody-mobile-xuc-xac-xoay-coffee-tp-hcm.jpg",
 "address": "157/1 Nguyễn Chí Thanh, Quận 5, TP. HCM",
 "type": "Café/Dessert",
 "location":
 {
  "lat":10.7606009,
  "lng":106.6708322
 }
 },
 {
 "name": "Phúc Long Coffee & Tea - 188 Trần Hưng Đạo",
 "img": "https://images.foody.vn/res/g5/48683/prof/s576x330/foody-mobile-phuc-long-1-jpg-380-636131772428730685.jpg",
 "address": "188 Trần Hưng Đạo, P. 11, Quận 5, TP. HCM",
 "type": "Café/Dessert",
 "location":
 {
  "lat":10.7526193,
  "lng":106.6643961
 }
 },
 {
 "name": "Phúc Long Coffee & Tea - Golden Plaza",
 "img": "https://images.foody.vn/res/g64/631401/prof/s576x330/foody-mobile-3-jpg-343-636216532386982372.jpg",
 "address": "Golden Plaza, 922 Nguyễn Trãi, P. 14, Quận 5, TP. HCM",
 "type": "Café/Dessert",
 "location":
 {
  "lat":10.7535982,
  "lng":106.6524874
 }
 },
 {
 "name": "Phúc Long Coffee & Tea - Nowzone",
 "img": "https://images.foody.vn/res/g17/167700/prof/s576x330/foody-mobile-f4ddeyme-jpg-293-635829363077439397.jpg",
 "address": "Tầng Trệt - Nowzone, 235 Nguyễn Văn Cừ, P. Nguyễn Cư Trinh, Quận 1, TP. HCM",
 "type": "Café/Dessert",
 "location":
 {
  "lat":10.7643646,
  "lng":106.6818139
 }
 },
 {
 "name": "Cheese Coffee - Hồng Bàng",
 "img": "https://images.foody.vn/res/g72/710932/prof/s576x330/foody-upload-api-foody-mobile-hong-bang-jpg-180620154932.jpg",
 "address": "307 Hồng Bàng, P. 11, Quận 5, TP. HCM",
 "type": "Café/Dessert",
 "location":
 {
  "lat":10.7547031,
  "lng":106.6602871
 }
 },
 {
 "name": "Starbucks Coffee - Lakai Building",
 "img": "https://media.foody.vn/res/g22/211131/prof/s/foody-mobile-foody-starbucks-coff-922-635912399324719351.jpg",
 "address": "98 Nguyễn Tri Phương, Quận 5, TP. HCM",
 "type": "Café/Dessert",
 "location":
 {
  "lat":10.7537358,
  "lng":106.6694149
 }
 },
 {
 "name": "Urban Station Coffee Takeaway - Nguyễn Trãi",
 "img": "https://images.foody.vn/res/g9/83037/prof/s576x330/foody-mobile-w3-jpg-984-635767249042565003.jpg",
 "address": "29 Nguyễn Trãi, Quận 5, TP. HCM",
 "type": "Café/Dessert",
 "location":
 {
  "lat":10.7589135,
  "lng":106.6807337
 }
 },
 {
 "name": "Koi Thé Café - The Garden Mall",
 "img": "https://images.foody.vn/res/g69/681679/prof/s576x330/foody-mobile-dfs-jpg-698-636384024909202878.jpg",
 "address": "Tầng Trệt The Garden Mall, 190 Hồng Bàng, P. 12, Quận 5, TP. HCM",
 "type": "Café/Dessert",
 "location":
 {
  "lat":10.75438,
  "lng":106.6541986
 }
 },
 {
 "name": "Royaltea Vietnam - Nguyễn Trãi",
 "img": "https://images.foody.vn/res/g70/692865/prof/s576x330/foody-mobile-foody-mobile-tra-jpg-474-636428172415792136.jpg",
 "address": "46 - 48 Nguyễn Trãi, P. 3, Quận 5, TP. HCM",
 "type": "Café/Dessert",
 "location":
 {
  "lat":10.7583576,
  "lng":106.6784001
 }
 }
 {
 "name": "L'angfarm Buffet - Trần Hưng Đạo",
 "img": "https://images.foody.vn/res/g22/215893/prof/s640x400/2018123152530-langfarm-buffet-tran-hung-dao-copy.jpg",
 "address": "771 - 773 - 775 Trần Hưng Đạo, P. 1, Quận 5, TP. HCM",
 "type": "Buffet",
 "location":
 {
  "lat":10.7552823,
  "lng":106.6818831
 }
 },
 {
 "name": "Mama BBQ - Buffet Nướng & Lẩu",
 "img": "https://images.foody.vn/res/g74/732238/prof/s576x330/foody-upload-api-foody-mobile-undefined-qmama-bbq--180416105937.jpg",
 "address": "635A Nguyễn Trãi, Quận 5, TP. HCM",
 "type": "Buffet",
 "location":
 {
  "lat":10.7632348,
  "lng":106.6867868
 }
 },
 {
 "name": "Hoàng Yến Buffet - The Garden Mall",
 "img": "https://images.foody.vn/res/g75/744407/prof/s576x330/foody-upload-api-foody-mobile-hoang-yen-buffet-jpg-180524173547.jpg",
 "address": "Zone C, Tầng 3 The Garden Mall, 190 Hồng Bàng, P. 12, Quận 5, TP. HCM",
 "type": "Buffet",
 "location":
 {
  "lat":10.7544186,
  "lng":106.6564656
 }
 },
 {
 "name": "Buffet Windsor - Cafe Central An Dong - Windsor Plaza",
 "img": "https://media.foody.vn/res/g1/8/prof/s/foody-mobile-dpxxrdae-jpg-176-635851879399811855.jpg",
 "address": "Windsor Plaza, 18 An Dương Vương, Quận 5, TP. HCM",
 "type": "Buffet",
 "location":
 {
  "lat":10.7579071,
  "lng":106.6735312
 }
 },
 {
 "name": "Thiên Du & Sky Sushi - Trần Hưng Đạo",
 "img": "https://images.foody.vn/res/g3/26626/prof/s576x330/foody-mobile-sky-sushi-tp-hcm.jpg",
 "address": "1089A Trần Hưng Đạo, P. 5, Quận 5, TP. HCM",
 "type": "Ăn vặt/Vỉa hè",
 "location":
 {
  "lat":10.7531762,
  "lng":106.674002
 }
 },
 {
 "name": "Dì Lan - Cacao Dừa",
 "img": "https://images.foody.vn/res/g18/172494/prof/s640x400/foody-mobile-1v6u0qy8-jpg-963-635794044096061380.jpg",
 "address": "329 Hùng Vương, P. 9, Quận 5, TP. HCM",
 "type": "Ăn vặt/Vỉa hè",
 "location":
 {
  "lat":10.7571524,
  "lng":106.6686813
 }
 },
 {
 "name": "Bánh Tráng Nướng Đà Lạt NTP",
 "img": "https://images.foody.vn/res/g8/73400/prof/s640x400/foody-mobile-6-jpg-651-636268937776123177.jpg",
 "address": "285 Hùng Vương, P 9, Quận 5, TP. HCM",
 "type": "Ăn vặt/Vỉa hè",
 "location":
 {
  "lat":10.7581508,
  "lng":106.6705809
 }
 },
 {
 "name": "Chè Hà Ký - Châu Văn Liêm",
 "img": "https://images.foody.vn/res/g1/4371/prof/s576x330/foody-mobile-che-ha-ky-jpg-382-636124203638629780.jpg",
 "address": "138 Châu Văn Liêm, P. 11, Quận 5, TP. HCM",
 "type": "Ăn vặt/Vỉa hè",
 "location":
 {
  "lat":10.7541275,
  "lng":106.6585196
 }
 },
 {
 "name": "Lê Gia - Hongkong Street Food",
 "img": "https://images.foody.vn/res/g19/187227/prof/s576x330/foody-mobile-12-jpg-293-636156625471452716.jpg",
 "address": "623 - 625 Nguyễn Trãi, P.11, Quận 5, TP. HCM",
 "type": "Ăn vặt/Vỉa hè",
 "location":
 {
  "lat":10.7536722,
  "lng":106.6658551
 }
 },
 {
 "name": "Lu's Corner - Hong Kong Street Food",
 "img": "https://images.foody.vn/res/g28/277507/prof/s640x400/foody-mobile-lu-jpg-538-636106778146455000.jpg",
 "address": "319 Hùng Vương, P. 9, Quận 5, TP. HCM",
 "type": "Ăn vặt/Vỉa hè",
 "location":
 {
  "lat":10.7581023,
  "lng":106.6702992
 }
 },
 {
 "name": "Cacao Dừa 136",
 "img": "https://images.foody.vn/res/g13/125061/prof/s640x400/foody-upload-api-foody-mobile-dff-jpg-180521181402.jpg",
 "address": "136/1 Nguyễn Tri Phương, P. 9, Quận 5, TP. HCM",
 "type": "Ăn vặt/Vỉa hè",
 "location":
 {
  "lat":10.7581352,
  "lng":106.6694218
 }
 },
 {
 "name": "Hải Thanh - Há Cảo & Xíu Mại",
 "img": "https://images.foody.vn/res/g7/69842/prof/s576x330/foody-mobile-hai-thanh-jpg-599-636059046602297803.jpg",
 "address": "167 Bùi Hữu Nghĩa, P. 7, Quận 5, TP. HCM",
 "type": "Ăn vặt/Vỉa hè",
 "location":
 {
  "lat":10.7550643,
  "lng":106.6743462
 }
 },
 {
 "name": "Quán Ù Pa - Kem Cá Phô Mai - Nguyễn Án",
 "img": "https://images.foody.vn/res/g25/245629/prof/s576x330/foody-mobile-c2-jpg-497-636015211714100994.jpg",
 "address": "9A Nguyễn Án, P. 11, Quận 5, TP. HCM",
 "type": "Ăn vặt/Vỉa hè",
 "location":
 {
  "lat":10.7525634,
  "lng":106.6604818
 }
 },
 {
 "name": "Takoyaki - An Dương Vương",
 "img": "https://images.foody.vn/res/g13/128474/prof/s576x330/foody-mobile-14-jpg-823-635635721425782898.jpg",
 "address": "465 An Dương Vương, Quận 5, TP. HCM",
 "type": "Ăn vặt/Vỉa hè",
 "location":
 {
  "lat":10.7580828,
  "lng":106.6759996
 }
 },
 {
 "name": "Bánh Mì Kẹp Kem - Phan Văn Trị",
 "img": "https://images.foody.vn/res/g11/101876/prof/s576x330/foody-mobile-zs8xbxt7-jpg-901-636232960681952260.jpg",
 "address": "Xe Bán Dạo, Phan Văn Trị & Huỳnh Mẫn Đạt, Quận 5, TP. HCM",
 "type": "Ăn vặt/Vỉa hè",
 "location":
 {
  "lat":10.7553792,
  "lng":106.6765582
 }
 },
 {
 "name": "Lovi - Sake Lắc - Nguyễn Văn Cừ",
 "img": "https://images.foody.vn/res/g22/219339/prof/s640x400/foody-mobile-12932684_90060478672-210-636021917809281224.jpg	",
 "address": "147A Nguyễn Văn Cừ, P. 2, Quận 5, TP. HCM",
 "type": "Ăn vặt/Vỉa hè",
 "location":
 {
  "lat":10.7575731,
  "lng":106.6845039
 }
 },
 {
 "name": "Mỳ 7 Tô - Nguyễn Duy Dương",
 "img": "https://images.foody.vn/res/g17/169305/prof/s640x400/foody-mobile-3-jpg-724-636320074128519836.jpg",
 "address": "Lầu 2, 20 Nguyễn Duy Dương, P. 8, Quận 5, TP. HCM",
 "type": "Quán ăn",
 "location":
 {
  "lat":10.7560276,
  "lng":106.6719901
 }
 },
 {
 "name": "Thần Rồng Mì Nhật - Ramen",
 "img": "https://images.foody.vn/res/g9/84987/prof/s640x400/foody-mobile-10-jpg.jpg",
 "address": "245 Trần Hưng Đạo, P. 10, Quận 5, TP. HCM",
 "type": "Quán ăn",
 "location":
 {
  "lat":10.7519448,
  "lng":106.6635187
 }
 },
 {
 "name": "Lẩu Nướng Thái Lan Số 7 - Poi Pet",
 "img": "https://images.foody.vn/res/g5/49710/prof/s640x400/foody-mobile-untitled-1-jpg-314-636207625482110972.jpg",
 "address": "31/A2 Hùng Vương, Quận 5, TP. HCM",
 "type": "Quán ăn",
 "location":
 {
  "lat":10.758416,
  "lng":106.6708829
 }
 },
 {
 "name": "Quán Sâm - Mì Vịt Tiềm Sủi Cảo",
 "img": "https://images.foody.vn/res/g5/44140/prof/s576x330/foody-mobile-foody-mobile-c2-jpg-.jpg",
 "address": "409/12 Nguyễn Trãi, Quận 5, TP. HCM",
 "type": "Quán ăn",
 "location":
 {
  "lat":10.7587156,
  "lng":106.6815391
 }
 },
 {
 "name": "Trần Quang Ký - Vịt Quay Sốt Tiêu Đen",
 "img": "https://images.foody.vn/res/g7/67455/prof/s576x330/foody-mobile-tran-quang-ky-mb-jpg-348-635738931856233888.jpg",
 "address": "390 Trần Phú, P. 7, Quận 5, TP. HCM",
 "type": "Quán ăn",
 "location":
 {
  "lat":10.7530577,
  "lng":106.6684993
 }
 },
 {
 "name": "Lẩu Mắm Quán Vy",
 "img": "https://images.foody.vn/res/g5/46397/prof/s576x330/foody-mobile-19-1-jpg-858-635537393539011687.jpg",
 "address": "106 Trần Bình Trọng, P. 1, Quận 5, TP. HCM",
 "type": "Quán ăn",
 "location":
 {
  "lat":10.7550224,
  "lng":106.6816449
 }
 },
 {
 "name": "Quán Cô Út - Bò Né - Lê Hồng Phong",
 "img": "https://images.foody.vn/res/g20/197017/prof/s640x400/foody-mobile-20107_16008275635158-139-635862898899879082.jpg",
 "address": "008 Chung Cư Phan Văn Trị, Lê Hồng Phong, Quận 5, TP. HCM",
 "type": "Quán ăn",
 "location":
 {
  "lat":10.7562878,
  "lng":106.6778807
 }
 },
 {
 "name": "Quán Ăn Bảo Anh - Đặc Biệt Gà Ta",
 "img": "https://images.foody.vn/res/g1/1389/prof/s576x330/foody-mobile-foody-album11921708_-799-635787715625598400.jpg",
 "address": "131 Trần Phú, Quận 5, TP. HCM",
 "type": "Quán ăn",
 "location":
 {
  "lat":10.760215,
  "lng":106.6768224
 }
 },
 {
 "name": "BangKy - Mì Cá Viên Cari",
 "img": "https://images.foody.vn/res/g5/48474/prof/s576x330/foody-mobile-bangky-jpg-186-636130930158456541.jpg",
 "address": "436 Nguyễn Trãi, P. 7, Quận 5, TP. HCM",
 "type": "Quán ăn",
 "location":
 {
  "lat":10.7552529,
  "lng":106.6724005
 }
 },
 {
 "name": "Bún Đậu Tràng An - Nguyễn Duy Dương",
 "img": "https://images.foody.vn/res/g17/162950/prof/s576x330/foody-mobile-zdfaoeq7-jpg-246-635941795955865605.jpg",
 "address": "51 Nguyễn Duy Dương, P. 8, Quận 5, TP. HCM",
 "type": "Quán ăn",
 "location":
 {
  "lat":10.7562821,
  "lng":106.6716257
 }
 }
]}



/*
 {
 "name": "",
 "img": "",
 "address": "",
 "type": "Quán ăn",
 "location":
 {
  "lat":,
  "lng":
 }
 },
 */
